splunk_tracer-0.1.0.dist-info/DESCRIPTION.rst
splunk_tracer-0.1.0.dist-info/METADATA
splunk_tracer-0.1.0.dist-info/RECORD
splunk_tracer-0.1.0.dist-info/WHEEL
splunk_tracer-0.1.0.dist-info/metadata.json
splunk_tracer-0.1.0.dist-info/top_level.txt
splunktracing/__init__.py
splunktracing/collector.py
splunktracing/constants.py
splunktracing/converter.py
splunktracing/http_connection.py
splunktracing/http_converter.py
splunktracing/lightstep_carrier_pb2.py
splunktracing/propagation.py
splunktracing/recorder.py
splunktracing/splunk_binary_propagator.py
splunktracing/tracer.py
splunktracing/util.py
splunktracing/version.py
